heliokos/__init__.py
heliokos/app.py
heliokos/domain/__init__.py
heliokos/domain/core.py
heliokos/domain/helioregion.ttl
heliokos/infra/__init__.py
heliokos/infra/agu_index_terms.ttl
heliokos/infra/core.py
heliokos/infra/openalex.ttl
heliokos/infra/static/csvw.ttl
heliokos/infra/static/dc.ttl
heliokos/infra/static/dcterms.ttl
heliokos/infra/static/foaf.ttl
heliokos/infra/static/org.ttl
heliokos/infra/static/owl.ttl
heliokos/infra/static/prov.ttl
heliokos/infra/static/qudt-constant.ttl
heliokos/infra/static/qudt-datatype.ttl
heliokos/infra/static/qudt-dimensionvector.ttl
heliokos/infra/static/qudt-quantitykind.ttl
heliokos/infra/static/qudt-soqk.ttl
heliokos/infra/static/qudt-sou.ttl
heliokos/infra/static/qudt-unit.ttl
heliokos/infra/static/qudt.ttl
heliokos/infra/static/rdf.ttl
heliokos/infra/static/rdfa11.json
heliokos/infra/static/rdfs.ttl
heliokos/infra/static/schemaorg.ttl
heliokos/infra/static/shacl.ttl
heliokos/infra/static/skos.ttl
heliokos/ui/__init__.py
heliokos/ui/html.py
heliokos/ui/main.py
heliokos/ui/static/htmx.min.js
heliokos/ui/templates/base.html
heliokos/ui/templates/concept.html
heliokos/ui/templates/concept_neighborhood.html
heliokos/ui/templates/home.html
heliokos/ui/templates/scheme.html
heliokos-0.0.10.dist-info/METADATA
heliokos-0.0.10.dist-info/WHEEL
heliokos-0.0.10.dist-info/licenses/LICENSE
heliokos-0.0.10.dist-info/RECORD
